Metadata-Version: 1.1
Name: qdatum
Version: 0.0.5
Summary: API wrapper for the qdatum platform
Home-page: https://github.com/qdatum/qdatum-python-driver
Author: Itamar Maltz
Author-email: ism@qdatum.io
License: MIT
Download-URL: https://github.com/qdatum/qdatum-python-driver/tarball/0.0.5
Keywords: qdatum api
Platform: any
Classifier: Intended Audience :: Developers
Classifier: Operating System :: OS Independent
Classifier: Programming Language :: Python
Classifier: Topic :: Software Development :: Libraries :: Python Modules
Classifier: License :: OSI Approved :: MIT License
